LICENSE
README.md
setup.py
tcp_over_websocket/__init__.py
tcp_over_websocket/run_tcp_over_websocket_service.py
tcp_over_websocket/winsvc_tcp_over_websocket_service.py
tcp_over_websocket.egg-info/PKG-INFO
tcp_over_websocket.egg-info/SOURCES.txt
tcp_over_websocket.egg-info/dependency_links.txt
tcp_over_websocket.egg-info/entry_points.txt
tcp_over_websocket.egg-info/not-zip-safe
tcp_over_websocket.egg-info/requires.txt
tcp_over_websocket.egg-info/top_level.txt
tcp_over_websocket/config/__init__.py
tcp_over_websocket/config/file_config.py
tcp_over_websocket/config/file_config_abc.py
tcp_over_websocket/config/file_config_data_exchange.py
tcp_over_websocket/config/file_config_service.py
tcp_over_websocket/config/file_config_tcp_connect_tunnel.py
tcp_over_websocket/config/file_config_tcp_listen_tunnel.py
tcp_over_websocket/controllers/__init__.py
tcp_over_websocket/controllers/active_remote_controller.py
tcp_over_websocket/controllers/tunnel_connection_controller.py
tcp_over_websocket/controllers/tunnel_controller.py
tcp_over_websocket/controllers/websocket_client_controller.py
tcp_over_websocket/controllers/websocket_server_controller.py
tcp_over_websocket/tcp_tunnel/__init__.py
tcp_over_websocket/tcp_tunnel/tcp_tunnel_abc.py
tcp_over_websocket/tcp_tunnel/tcp_tunnel_connect.py
tcp_over_websocket/tcp_tunnel/tcp_tunnel_listen.py
tcp_over_websocket/tcp_tunnel/tunnel_factory.py
tcp_over_websocket/tcp_tunnel/tunnel_protocol.py
tcp_over_websocket/util/__init__.py
tcp_over_websocket/util/log_util.py
tcp_over_websocket/util/restart_util.py
tcp_over_websocket/util/vortex_util.py
tcp_over_websocket/util/windows_util.py
tests/test_suite_1_basic_echo.py
tests/test_suite_2_basic_failover.py
tests/test_suite_3_data_quality.py
tests/test_suite_4_ping_pong.py
tests/test_suite_5_concurrent_connections.py
tests/test_suite_6_failover_impact.py
tests/test_suite_7_maximum_punishment.py