Metadata-Version: 2.4
Name: tcp-over-websocket
Version: 1.1.1
Summary: TCP over HTTPS Upgraded Websocket with Mutual TLS
Home-page: https://github.com/Synerty/tcp-over-websocket
Download-URL: https://codeload.github.com/Synerty/tcp-over-websocket/zip/refs/heads/master
Author: Synerty
Author-email: contact@synerty.com
Keywords: TCP,Websocket,MutualTLS,synerty,tunnel,proxy
Classifier: Development Status :: 4 - Beta
Classifier: Intended Audience :: Developers
Classifier: Intended Audience :: System Administrators
Classifier: License :: OSI Approved :: MIT License
Classifier: Operating System :: OS Independent
Classifier: Programming Language :: Python :: 3
Classifier: Programming Language :: Python :: 3.9
Classifier: Topic :: Internet :: WWW/HTTP
Classifier: Topic :: System :: Networking
Classifier: Topic :: Software Development :: Libraries :: Python Modules
Requires-Python: >=3.9
License-File: LICENSE
Requires-Dist: vortexpy==3.4.3
Requires-Dist: txhttputil==1.2.8
Requires-Dist: json-cfg-rw==0.5.0
Requires-Dist: twisted[tls]==22.10.0
Requires-Dist: reactivex==4.0.4
Dynamic: author
Dynamic: author-email
Dynamic: classifier
Dynamic: description
Dynamic: description-content-type
Dynamic: download-url
Dynamic: home-page
Dynamic: keywords
Dynamic: license-file
Dynamic: requires-dist
Dynamic: requires-python
Dynamic: summary
